CHANGELOG.md
MANIFEST.in
README.md
VERSION
metadocuments.py
setup.py
metadocuments.egg-info/PKG-INFO
metadocuments.egg-info/SOURCES.txt
metadocuments.egg-info/dependency_links.txt
metadocuments.egg-info/requires.txt
metadocuments.egg-info/top_level.txt