Metadata-Version: 2.1
Name: metadocuments
Version: 1.3.0
Summary: Library for defining structured documents (JSON, YAML) as classes. Created as a metaprogramming exercise
Home-page: https://gitlab.com/blissfulreboot/python/metadocuments
Author: Aki Mäkinen
Author-email: nenshou.sora@gmail.com
License: MIT
Platform: UNKNOWN
Classifier: Development Status :: 3 - Alpha
Classifier: Intended Audience :: Developers
Classifier: Topic :: Software Development
Classifier: License :: OSI Approved :: MIT License
Classifier: Programming Language :: Python :: 3
Classifier: Programming Language :: Python :: 3.6
Classifier: Programming Language :: Python :: 3.7
Classifier: Programming Language :: Python :: 3.8
